vjson/__init__.py
vjson/compat.py
vjson/tests/__init__.py
vjson/tests/test_it.py
vjson-0.1.dist-info/DESCRIPTION.rst
vjson-0.1.dist-info/entry_points.txt
vjson-0.1.dist-info/METADATA
vjson-0.1.dist-info/metadata.json
vjson-0.1.dist-info/namespace_packages.txt
vjson-0.1.dist-info/RECORD
vjson-0.1.dist-info/top_level.txt
vjson-0.1.dist-info/WHEEL
