Metadata-Version: 2.0
Name: vjson
Version: 0.1
Summary: vjson creates an object to serialize the only of the type specified in JSONSchema. It works like a json module.
Home-page: https://github.com/TakesxiSximada/vjson
Author: TakesxiSximada
Author-email: takesxi.sximada@gmail.com
License: MIT
Download-URL: https://github.com/TakesxiSximada/vjson/master.zip
Platform: any
Classifier: Development Status :: 4 - Beta
Classifier: Intended Audience :: Developers
Classifier: Intended Audience :: Information Technology
Classifier: Intended Audience :: System Administrators
Classifier: Natural Language :: English
Classifier: Operating System :: MacOS :: MacOS X
Classifier: Operating System :: Microsoft :: Windows
Classifier: Operating System :: POSIX
Classifier: Programming Language :: Python :: 2.7
Classifier: Programming Language :: Python :: 3.4
Requires-Dist: setuptools
Requires-Dist: six
Requires-Dist: jsonschema
Requires-Dist: nose
Requires-Dist: tox
